_CHJ/LICENSE
_CHJ/Media.py
_CHJ/Parameters.py
_CHJ/README.rst
_CHJ/VERSION.py
_CHJ/__init__.py
_CHJ/setup.cfg
_CHJ/setup.py
_CHJ/_CSS/CS.py
_CHJ/_CSS/Calc.py
_CHJ/_CSS/Color.py
_CHJ/_CSS/Length.py
_CHJ/_CSS/Media.py
_CHJ/_CSS/Property.py
_CHJ/_CSS/Rule.py
_CHJ/_CSS/Shape.py
_CHJ/_CSS/Style_Sheet.py
_CHJ/_CSS/_TRBL_.py
_CHJ/_CSS/__init__.py
_CHJ/_CSS/import_CSS.py
CHJ-3.9.dist-info/LICENSE
CHJ-3.9.dist-info/METADATA
CHJ-3.9.dist-info/WHEEL
CHJ-3.9.dist-info/top_level.txt
CHJ-3.9.dist-info/RECORD
