Metadata-Version: 2.1
Name: CHJ
Version: 3.9
Summary: Package for CSS/HTML/Javascript support.
Home-page: https://codeberg.org/tanzer/tapyr
Author: Christian Tanzer
Author-email: tanzer@swing.co.at
License: BSD License
Platform: Any
Classifier: Development Status :: 5 - Production/Stable
Classifier: License :: OSI Approved :: BSD License
Classifier: Operating System :: OS Independent
Classifier: Programming Language :: Python
Classifier: Intended Audience :: Developers
Classifier: Topic :: Internet :: WWW/HTTP :: Dynamic Content
Classifier: Topic :: Software Development :: Libraries :: Python Modules
Classifier: Topic :: Text Processing :: Markup :: HTML
Requires-Python: >=3.9
License-File: LICENSE
Requires-Dist: TFL (>=3)
Provides-Extra: minified
Requires-Dist: rcssmin ; extra == 'minified'
Requires-Dist: rjsmin ; extra == 'minified'
Provides-Extra: minified_debian_slow
Requires-Dist: cssmin ; extra == 'minified_debian_slow'
Requires-Dist: jsmin ; extra == 'minified_debian_slow'
